iot_agent/__init__.py
iot_agent/main.py
iot_agent-0.1.3.dist-info/METADATA
iot_agent-0.1.3.dist-info/WHEEL
iot_agent-0.1.3.dist-info/entry_points.txt
iot_agent-0.1.3.dist-info/RECORD
