Metadata-Version: 2.1
Name: iot-agent
Version: 0.1.3
Summary: Iteration of Thought LLM Agent
Home-page: https://github.com/raphaelmansuy/iteration_of_thought
License: MIT
Keywords: llm,agent,openai,litellm
Author: Raphael MANSUY
Author-email: raphael.mansuy@gmail.com
Requires-Python: >=3.12,<4.0
Classifier: Development Status :: 4 - Beta
Classifier: Intended Audience :: Developers
Classifier: License :: OSI Approved :: MIT License
Classifier: Programming Language :: Python :: 3
Classifier: Programming Language :: Python :: 3.12
Classifier: Programming Language :: Python :: 3.10
Classifier: Programming Language :: Python :: 3.11
Classifier: Programming Language :: Python :: 3.8
Classifier: Programming Language :: Python :: 3.9
Requires-Dist: litellm (>=1.46.8,<2.0.0)
Requires-Dist: loguru (>=0.7.2,<0.8.0)
Requires-Dist: openai (>=1.46.1,<2.0.0)
Requires-Dist: rich (>=13.8.1,<14.0.0)
Requires-Dist: setuptools (>=75.1.0,<76.0.0)
Project-URL: Repository, https://github.com/raphaelmansuy/iteration_of_tought
